gcmb_publisher/__init__.py
gcmb_publisher/py.typed
gcmb_publisher-0.6.3.dist-info/METADATA
gcmb_publisher-0.6.3.dist-info/WHEEL
gcmb_publisher-0.6.3.dist-info/RECORD
