Metadata-Version: 2.4
Name: gcmb-publisher
Version: 0.6.3
Summary: Add your description here
Author-email: Stefan Hudelmaier <stefan@huditech.com>
Requires-Python: >=3.12
Requires-Dist: paho-mqtt>=2.1.0
